LICENSE
MANIFEST.in
README.md
setup.py
harvest_vocab.egg-info/PKG-INFO
harvest_vocab.egg-info/SOURCES.txt
harvest_vocab.egg-info/dependency_links.txt
harvest_vocab.egg-info/requires.txt
harvest_vocab.egg-info/top_level.txt
vocab/__init__.py
vocab/managers.py
vocab/models.py
vocab/operators.py
vocab/resources.py
vocab/settings.py
vocab/translators.py
vocab/urls.py