Metadata-Version: 1.0
Name: harvest-vocab
Version: 2.0.0
Summary: A Harvest Stack app for modeling hierarchical data
Home-page: https://github.com/cbmi/harvest-vocab/
Author: Byron Ruth
Author-email: b@devel.io
License: BSD
Keywords: django harvest avocado cilantro vocabulary hierarchical
Platform: UNKNOWN
Classifier: Development Status :: 5 - Production/Stable
Classifier: License :: OSI Approved :: BSD License
Classifier: Programming Language :: Python :: 2.6
Classifier: Programming Language :: Python :: 2.7
Classifier: Framework :: Django
Classifier: Topic :: Internet :: WWW/HTTP
Classifier: Intended Audience :: Developers
Classifier: Intended Audience :: Science/Research
Classifier: Intended Audience :: Healthcare Industry
